wafer/GUIDE.md
wafer/__init__.py
wafer/agent_defaults.py
wafer/analytics.py
wafer/api_client.py
wafer/auth.py
wafer/autotuner.py
wafer/baseline.py
wafer/billing.py
wafer/cli.py
wafer/cli_instructions.py
wafer/config.py
wafer/corpus.py
wafer/evaluate.py
wafer/global_config.py
wafer/gpu_run.py
wafer/inference.py
wafer/kernel_scope.py
wafer/ncu_analyze.py
wafer/nsys_analyze.py
wafer/nsys_profile.py
wafer/output.py
wafer/problems.py
wafer/rocprof_compute.py
wafer/rocprof_sdk.py
wafer/rocprof_systems.py
wafer/specs_cli.py
wafer/ssh_keys.py
wafer/target_lock.py
wafer/targets.py
wafer/targets_cli.py
wafer/targets_ops.py
wafer/trace_compare.py
wafer/tracelens.py
wafer/wevin_cli.py
wafer/workspaces.py
wafer/skills/wafer-guide/SKILL.md
wafer/templates/__init__.py
wafer/templates/aiter_optimize.py
wafer/templates/ask_docs.py
wafer/templates/optimize_kernel.py
wafer/templates/optimize_kernelbench.py
wafer/templates/optimize_vllm.py
wafer/templates/trace_analyze.py
wafer/tests/test_eval_cli_parity.py
wafer_cli-0.2.38.dist-info/METADATA
wafer_cli-0.2.38.dist-info/WHEEL
wafer_cli-0.2.38.dist-info/entry_points.txt
wafer_cli-0.2.38.dist-info/top_level.txt
wafer_cli-0.2.38.dist-info/RECORD
