Metadata-Version: 2.4
Name: wafer-cli
Version: 0.2.38
Summary: CLI for running GPU workloads, managing remote workspaces, and evaluating/optimizing kernels
Requires-Python: >=3.11
Requires-Dist: typer>=0.12.0
Requires-Dist: trio>=0.24.0
Requires-Dist: trio-asyncio>=0.15.0
Requires-Dist: wafer-core>=0.1.0
Requires-Dist: perfetto>=0.16.0
Requires-Dist: posthog>=3.0.0
Provides-Extra: dev
Requires-Dist: pytest>=8.0.0; extra == "dev"
Requires-Dist: pytest-cov>=4.1.0; extra == "dev"
Requires-Dist: diff-cover>=8.0.0; extra == "dev"
Requires-Dist: ruff>=0.4.0; extra == "dev"
